Phidgeter-1.0.1.dist-info/DESCRIPTION.rst
Phidgeter-1.0.1.dist-info/RECORD
Phidgeter-1.0.1.dist-info/metadata.json
Phidgeter-1.0.1.dist-info/WHEEL
Phidgeter-1.0.1.dist-info/top_level.txt
Phidgeter-1.0.1.dist-info/METADATA
phidgeter/__init__.py
phidgeter/relay.py
