Metadata-Version: 2.0
Name: Phidgeter
Version: 1.0.1
Summary: logging and convenience functions for phidgets
Home-page: https://github.com/nharringtonwasatch/Phidgeter
Author: Nathan Harrington
Author-email: nharrington@wasatchphotonics.com
License: UNKNOWN
Download-URL: https://github.com/nharringtonwasatch/Phidgeter
Platform: UNKNOWN
Requires-Dist: nose
Requires-Dist: testfixtures
Requires-Dist: phidgets
